avdeepfake1m-0.0.4.dist-info/METADATA
avdeepfake1m-0.0.4.dist-info/WHEEL
avdeepfake1m-0.0.4.dist-info/licenses/LICENSE
avdeepfake1m/__init__.py
avdeepfake1m/_evaluation.cp313-win_amd64.pyd
avdeepfake1m/evaluation/__init__.py
avdeepfake1m/evaluation/__init__.pyi
avdeepfake1m/evaluation/auc.py
avdeepfake1m/loader.py
avdeepfake1m/utils.py
avdeepfake1m-0.0.4.dist-info/RECORD
