Metadata-Version: 2.4
Name: avdeepfake1m
Version: 0.0.4
Classifier: Programming Language :: Rust
Classifier: Programming Language :: Python :: Implementation :: CPython
Classifier: Programming Language :: Python :: 3
Classifier: Programming Language :: Python :: 3.7
Classifier: Programming Language :: Python :: 3.8
Classifier: Programming Language :: Python :: 3.9
Classifier: Programming Language :: Python :: 3.10
Classifier: Programming Language :: Python :: 3.11
Classifier: Programming Language :: Python :: 3.12
Classifier: License :: Other/Proprietary License
Classifier: Operating System :: OS Independent
Classifier: Intended Audience :: Developers
Classifier: Topic :: Scientific/Engineering :: Artificial Intelligence
Classifier: Topic :: Multimedia :: Video
Classifier: Topic :: Utilities
Requires-Dist: torch
Requires-Dist: lightning>=2
Requires-Dist: tqdm
Requires-Dist: einops
Requires-Dist: opencv-python
Requires-Dist: numpy>=1,<2
Requires-Dist: torchvision
Requires-Dist: torchaudio
Requires-Dist: av
Requires-Dist: pandas~=2.0
Requires-Dist: torchmetrics~=1.0
License-File: LICENSE
Keywords: pytorch,AI
Author-email: ControlNet <smczx@hotmail.com>
Requires-Python: >=3.7
Project-URL: Homepage, https://github.com/ControlNet/AV-Deepfake1M
Project-URL: Source Code, https://github.com/ControlNet/AV-Deepfake1M
Project-URL: Bug Tracker, https://github.com/ControlNet/AV-Deepfake1M/issues
